uwsgi.py
uwsgi_stub-0.1.2.dist-info/DESCRIPTION.rst
uwsgi_stub-0.1.2.dist-info/METADATA
uwsgi_stub-0.1.2.dist-info/RECORD
uwsgi_stub-0.1.2.dist-info/WHEEL
uwsgi_stub-0.1.2.dist-info/metadata.json
uwsgi_stub-0.1.2.dist-info/top_level.txt
uwsgi_stub-0.1.2.dist-info/zip-safe
