Metadata-Version: 2.0
Name: uwsgi-stub
Version: 0.1.2
Summary: A stub file with correct signatures and docstrings for the python uwsgi module
Home-page: https://github.com/dakra/uwsgi-stub
Author: Daniel Kraus
Author-email: dakra-python@tr0ll.net
License: ISC
Keywords: uwsgi
Platform: UNKNOWN
Classifier: Development Status :: 4 - Beta
Classifier: Intended Audience :: Developers
Classifier: License :: OSI Approved :: ISC License (ISCL)
Classifier: Topic :: Internet :: WWW/HTTP :: WSGI
Classifier: Programming Language :: Python :: 2
Classifier: Programming Language :: Python :: 3
Classifier: Topic :: Software Development :: Libraries :: Python Modules
